ssh_cli/__init__.py
ssh_cli/__main__.py
ssh_cli/cmds/__init__.py
ssh_cli/cmds/cleanup.py
ssh_cli/cmds/connect.py
ssh_cli/cmds/create.py
ssh_cli/cmds/delete.py
ssh_cli/cmds/editor.py
ssh_cli/cmds/interface.py
ssh_cli/cmds/list.py
ssh_cli/cmds/show_host.py
ssh_cli/config.py
ssh_cli/lib.py
ssh_cli/validation.py
ssh_cli-2.3.5.dist-info/LICENSE
ssh_cli-2.3.5.dist-info/METADATA
ssh_cli-2.3.5.dist-info/WHEEL
ssh_cli-2.3.5.dist-info/entry_points.txt
ssh_cli-2.3.5.dist-info/RECORD
