Metadata-Version: 2.1
Name: ssh-cli
Version: 2.3.5
Summary: cli to manage the ssh config file
Home-page: https://github.com/ValentinKolb/ssh-cli
License: MIT
Keywords: ssh,cli,config
Author: valentinkolb
Author-email: valentin.kolb@uni-ulm.de
Requires-Python: >=3.10,<4.0
Classifier: Environment :: Console
Classifier: License :: OSI Approved :: MIT License
Classifier: Operating System :: OS Independent
Classifier: Programming Language :: Python :: 3
Classifier: Programming Language :: Python :: 3.10
Classifier: Programming Language :: Python :: 3.11
Classifier: Programming Language :: Python :: 3.12
Requires-Dist: inquirer (>=3.2.4,<4.0.0)
Requires-Dist: prettytable (>=3.10.0,<4.0.0)
Requires-Dist: sshconf (>=0.2.5,<0.3.0)
Requires-Dist: termcolor (>=2.4.0,<3.0.0)
Requires-Dist: validators (>=0.24.0,<0.25.0)
Project-URL: Repository, https://github.com/ValentinKolb/ssh-cli
